{
  "schema": "hourly_report_v1",
  "timezone": "Africa/Johannesburg",
  "published_at_utc": "2026-03-09T11:00:25+00:00",
  "published_at_local": "2026-03-09T13:00:25+02:00",
  "signal": {
    "date": "2026-03-09",
    "timezone": "Africa/Johannesburg",
    "published_at_local": "2026-03-09T13:00:25+02:00",
    "published_at_utc": "2026-03-09T11:00:25+00:00",
    "integrity": {
      "eth_usdt": {
        "symbol": "ETH-USDT",
        "source": "kucoin",
        "interval": "1hour",
        "requested_limit": 96,
        "returned_count": 96,
        "first_candle_open_time_local": "2026-03-05T14:00:00+02:00",
        "last_candle_open_time_local": "2026-03-09T13:00:00+02:00",
        "first_candle_open_time_utc": "2026-03-05T12:00:00+00:00",
        "last_candle_open_time_utc": "2026-03-09T11:00:00+00:00",
        "data_freshness_minutes": 0.43,
        "windows": {
          "last_24h": {
            "start_local": "2026-03-08T14:00:00+02:00",
            "end_local": "2026-03-09T13:00:00+02:00",
            "start_utc": "2026-03-08T12:00:00+00:00",
            "end_utc": "2026-03-09T11:00:00+00:00"
          },
          "prior_24h": {
            "start_local": "2026-03-07T14:00:00+02:00",
            "end_local": "2026-03-08T13:00:00+02:00",
            "start_utc": "2026-03-07T12:00:00+00:00",
            "end_utc": "2026-03-08T11:00:00+00:00"
          },
          "first_4h_current_24h": {
            "start_local": "2026-03-08T14:00:00+02:00",
            "end_local": "2026-03-08T17:00:00+02:00",
            "start_utc": "2026-03-08T12:00:00+00:00",
            "end_utc": "2026-03-08T15:00:00+00:00"
          }
        }
      },
      "eth_btc": {
        "symbol": "ETH-BTC",
        "source": "kucoin",
        "interval": "1hour",
        "requested_limit": 96,
        "returned_count": 96,
        "first_candle_open_time_local": "2026-03-05T13:00:00+02:00",
        "last_candle_open_time_local": "2026-03-09T12:00:00+02:00",
        "first_candle_open_time_utc": "2026-03-05T11:00:00+00:00",
        "last_candle_open_time_utc": "2026-03-09T10:00:00+00:00",
        "data_freshness_minutes": 60.43,
        "windows": {
          "last_24h": {
            "start_local": "2026-03-08T13:00:00+02:00",
            "end_local": "2026-03-09T12:00:00+02:00",
            "start_utc": "2026-03-08T11:00:00+00:00",
            "end_utc": "2026-03-09T10:00:00+00:00"
          },
          "prior_24h": {
            "start_local": "2026-03-07T13:00:00+02:00",
            "end_local": "2026-03-08T12:00:00+02:00",
            "start_utc": "2026-03-07T11:00:00+00:00",
            "end_utc": "2026-03-08T10:00:00+00:00"
          },
          "first_4h_current_24h": {
            "start_local": "2026-03-08T13:00:00+02:00",
            "end_local": "2026-03-08T16:00:00+02:00",
            "start_utc": "2026-03-08T11:00:00+00:00",
            "end_utc": "2026-03-08T14:00:00+00:00"
          }
        }
      }
    },
    "eth_usdt": {
      "high": 2022.18,
      "low": 1911.11,
      "open": 1951.33,
      "close": 1995.84,
      "gap_pct": 5.81
    },
    "eth_btc": {
      "high": 0.02969,
      "low": 0.0288,
      "open": 0.02907,
      "close": 0.0295,
      "gap_pct": 3.09
    },
    "prior_24h": {
      "high": 1991.05,
      "low": 1929.94
    },
    "first_4h_current_24h": {
      "high": 1954.8,
      "low": 1925.02
    },
    "atr_1h": {
      "value": 21.8329,
      "periods": 14,
      "method": "wilder",
      "trend": "rising"
    },
    "intraday_momentum": "up",
    "early_breakout": {
      "occurred": true,
      "description": "Broke below prior 24h low in first 4h (rolling).",
      "mode": "rolling"
    },
    "precomputed_signal": {
      "suggested_target": "3%",
      "confidence": "high",
      "notes": "Upside early breakout with momentum."
    }
  },
  "forecast": {
    "schema": "forecast_baseline_v1",
    "as_of_utc": "2026-03-09T11:00:25+00:00",
    "source": {
      "baseline_summary": "data/forecast/baseline_summary_v1.json",
      "labels": "data/labels/labels_v1.csv",
      "n_labels": 1572
    },
    "thresholds": [
      0.5,
      1.0,
      2.0,
      3.0,
      5.0
    ],
    "horizons": [
      12,
      24,
      36,
      48,
      60,
      72,
      84,
      96
    ],
    "targets": [
      {
        "target_pct": 0.5,
        "horizon_h": 12,
        "n_total": 1572,
        "n_hit": 1118,
        "p_hit": 0.711196,
        "t_hit_p25": 1.0,
        "t_hit_median": 2.0,
        "t_hit_p75": 5.0,
        "mdd_p25": -0.841375,
        "mdd_median": -0.29645,
        "mdd_p75": -0.054925
      },
      {
        "target_pct": 0.5,
        "horizon_h": 24,
        "n_total": 1572,
        "n_hit": 1267,
        "p_hit": 0.80598,
        "t_hit_p25": 1.0,
        "t_hit_median": 3.0,
        "t_hit_p75": 7.0,
        "mdd_p25": -0.9836,
        "mdd_median": -0.3775,
        "mdd_p75": -0.0852
      },
      {
        "target_pct": 0.5,
        "horizon_h": 36,
        "n_total": 1572,
        "n_hit": 1329,
        "p_hit": 0.84542,
        "t_hit_p25": 1.0,
        "t_hit_median": 3.0,
        "t_hit_p75": 8.0,
        "mdd_p25": -1.0755,
        "mdd_median": -0.4098,
        "mdd_p75": -0.0978
      },
      {
        "target_pct": 0.5,
        "horizon_h": 48,
        "n_total": 1572,
        "n_hit": 1347,
        "p_hit": 0.85687,
        "t_hit_p25": 1.0,
        "t_hit_median": 3.0,
        "t_hit_p75": 8.0,
        "mdd_p25": -1.1322,
        "mdd_median": -0.4191,
        "mdd_p75": -0.10185
      },
      {
        "target_pct": 0.5,
        "horizon_h": 60,
        "n_total": 1572,
        "n_hit": 1361,
        "p_hit": 0.865776,
        "t_hit_p25": 1.0,
        "t_hit_median": 3.0,
        "t_hit_p75": 9.0,
        "mdd_p25": -1.1619,
        "mdd_median": -0.4261,
        "mdd_p75": -0.1035
      },
      {
        "target_pct": 0.5,
        "horizon_h": 72,
        "n_total": 1572,
        "n_hit": 1390,
        "p_hit": 0.884224,
        "t_hit_p25": 1.0,
        "t_hit_median": 3.0,
        "t_hit_p75": 9.0,
        "mdd_p25": -1.24795,
        "mdd_median": -0.44684999999999997,
        "mdd_p75": -0.10585
      },
      {
        "target_pct": 0.5,
        "horizon_h": 84,
        "n_total": 1572,
        "n_hit": 1417,
        "p_hit": 0.901399,
        "t_hit_p25": 1.0,
        "t_hit_median": 3.0,
        "t_hit_p75": 10.0,
        "mdd_p25": -1.3343,
        "mdd_median": -0.4685,
        "mdd_p75": -0.11
      },
      {
        "target_pct": 0.5,
        "horizon_h": 96,
        "n_total": 1572,
        "n_hit": 1433,
        "p_hit": 0.911578,
        "t_hit_p25": 1.0,
        "t_hit_median": 3.0,
        "t_hit_p75": 10.0,
        "mdd_p25": -1.3625,
        "mdd_median": -0.4747,
        "mdd_p75": -0.1164
      },
      {
        "target_pct": 1.0,
        "horizon_h": 12,
        "n_total": 1572,
        "n_hit": 840,
        "p_hit": 0.534351,
        "t_hit_p25": 2.0,
        "t_hit_median": 4.0,
        "t_hit_p75": 7.0,
        "mdd_p25": -1.037525,
        "mdd_median": -0.4027,
        "mdd_p75": -0.081425
      },
      {
        "target_pct": 1.0,
        "horizon_h": 24,
        "n_total": 1572,
        "n_hit": 1025,
        "p_hit": 0.652036,
        "t_hit_p25": 2.0,
        "t_hit_median": 5.0,
        "t_hit_p75": 10.0,
        "mdd_p25": -1.1876,
        "mdd_median": -0.4764,
        "mdd_p75": -0.121
      },
      {
        "target_pct": 1.0,
        "horizon_h": 36,
        "n_total": 1572,
        "n_hit": 1141,
        "p_hit": 0.725827,
        "t_hit_p25": 2.0,
        "t_hit_median": 6.0,
        "t_hit_p75": 13.0,
        "mdd_p25": -1.3415,
        "mdd_median": -0.5158,
        "mdd_p75": -0.1489
      },
      {
        "target_pct": 1.0,
        "horizon_h": 48,
        "n_total": 1572,
        "n_hit": 1186,
        "p_hit": 0.754453,
        "t_hit_p25": 2.0,
        "t_hit_median": 6.0,
        "t_hit_p75": 15.0,
        "mdd_p25": -1.3572000000000002,
        "mdd_median": -0.5347999999999999,
        "mdd_p75": -0.158825
      },
      {
        "target_pct": 1.0,
        "horizon_h": 60,
        "n_total": 1572,
        "n_hit": 1226,
        "p_hit": 0.779898,
        "t_hit_p25": 3.0,
        "t_hit_median": 6.5,
        "t_hit_p75": 17.0,
        "mdd_p25": -1.3975,
        "mdd_median": -0.55185,
        "mdd_p75": -0.163975
      },
      {
        "target_pct": 1.0,
        "horizon_h": 72,
        "n_total": 1572,
        "n_hit": 1274,
        "p_hit": 0.810433,
        "t_hit_p25": 3.0,
        "t_hit_median": 7.0,
        "t_hit_p75": 19.0,
        "mdd_p25": -1.551375,
        "mdd_median": -0.5934999999999999,
        "mdd_p75": -0.1719
      },
      {
        "target_pct": 1.0,
        "horizon_h": 84,
        "n_total": 1572,
        "n_hit": 1308,
        "p_hit": 0.832061,
        "t_hit_p25": 3.0,
        "t_hit_median": 7.0,
        "t_hit_p75": 21.0,
        "mdd_p25": -1.652625,
        "mdd_median": -0.61615,
        "mdd_p75": -0.17689999999999997
      },
      {
        "target_pct": 1.0,
        "horizon_h": 96,
        "n_total": 1572,
        "n_hit": 1327,
        "p_hit": 0.844148,
        "t_hit_p25": 3.0,
        "t_hit_median": 7.0,
        "t_hit_p75": 22.0,
        "mdd_p25": -1.6953999999999998,
        "mdd_median": -0.6287,
        "mdd_p75": -0.18305
      },
      {
        "target_pct": 2.0,
        "horizon_h": 12,
        "n_total": 1572,
        "n_hit": 431,
        "p_hit": 0.274173,
        "t_hit_p25": 2.0,
        "t_hit_median": 5.0,
        "t_hit_p75": 8.0,
        "mdd_p25": -1.0958,
        "mdd_median": -0.4322,
        "mdd_p75": -0.1169
      },
      {
        "target_pct": 2.0,
        "horizon_h": 24,
        "n_total": 1572,
        "n_hit": 653,
        "p_hit": 0.415394,
        "t_hit_p25": 4.0,
        "t_hit_median": 8.0,
        "t_hit_p75": 15.0,
        "mdd_p25": -1.3315,
        "mdd_median": -0.5846,
        "mdd_p75": -0.1724
      },
      {
        "target_pct": 2.0,
        "horizon_h": 36,
        "n_total": 1572,
        "n_hit": 796,
        "p_hit": 0.506361,
        "t_hit_p25": 4.75,
        "t_hit_median": 11.0,
        "t_hit_p75": 21.0,
        "mdd_p25": -1.462375,
        "mdd_median": -0.6115,
        "mdd_p75": -0.18295
      },
      {
        "target_pct": 2.0,
        "horizon_h": 48,
        "n_total": 1572,
        "n_hit": 902,
        "p_hit": 0.573791,
        "t_hit_p25": 5.0,
        "t_hit_median": 13.0,
        "t_hit_p75": 27.0,
        "mdd_p25": -1.498075,
        "mdd_median": -0.6327499999999999,
        "mdd_p75": -0.2207
      },
      {
        "target_pct": 2.0,
        "horizon_h": 60,
        "n_total": 1572,
        "n_hit": 968,
        "p_hit": 0.615776,
        "t_hit_p25": 6.0,
        "t_hit_median": 15.0,
        "t_hit_p75": 31.0,
        "mdd_p25": -1.5380250000000002,
        "mdd_median": -0.68015,
        "mdd_p75": -0.24659999999999999
      },
      {
        "target_pct": 2.0,
        "horizon_h": 72,
        "n_total": 1572,
        "n_hit": 1030,
        "p_hit": 0.655216,
        "t_hit_p25": 6.0,
        "t_hit_median": 16.0,
        "t_hit_p75": 35.0,
        "mdd_p25": -1.621375,
        "mdd_median": -0.7902499999999999,
        "mdd_p75": -0.270175
      },
      {
        "target_pct": 2.0,
        "horizon_h": 84,
        "n_total": 1572,
        "n_hit": 1073,
        "p_hit": 0.68257,
        "t_hit_p25": 6.0,
        "t_hit_median": 17.0,
        "t_hit_p75": 37.0,
        "mdd_p25": -1.7868,
        "mdd_median": -0.8626,
        "mdd_p75": -0.2787
      },
      {
        "target_pct": 2.0,
        "horizon_h": 96,
        "n_total": 1572,
        "n_hit": 1110,
        "p_hit": 0.706107,
        "t_hit_p25": 7.0,
        "t_hit_median": 18.0,
        "t_hit_p75": 40.75,
        "mdd_p25": -1.879,
        "mdd_median": -0.9305,
        "mdd_p75": -0.29652500000000004
      },
      {
        "target_pct": 3.0,
        "horizon_h": 12,
        "n_total": 1572,
        "n_hit": 241,
        "p_hit": 0.153308,
        "t_hit_p25": 3.0,
        "t_hit_median": 5.0,
        "t_hit_p75": 8.0,
        "mdd_p25": -1.0609,
        "mdd_median": -0.4653,
        "mdd_p75": -0.1442
      },
      {
        "target_pct": 3.0,
        "horizon_h": 24,
        "n_total": 1572,
        "n_hit": 380,
        "p_hit": 0.24173,
        "t_hit_p25": 4.0,
        "t_hit_median": 9.0,
        "t_hit_p75": 17.0,
        "mdd_p25": -1.2542499999999999,
        "mdd_median": -0.5374,
        "mdd_p75": -0.15535
      },
      {
        "target_pct": 3.0,
        "horizon_h": 36,
        "n_total": 1572,
        "n_hit": 514,
        "p_hit": 0.326972,
        "t_hit_p25": 6.0,
        "t_hit_median": 14.0,
        "t_hit_p75": 25.0,
        "mdd_p25": -1.4657,
        "mdd_median": -0.6010500000000001,
        "mdd_p75": -0.193225
      },
      {
        "target_pct": 3.0,
        "horizon_h": 48,
        "n_total": 1572,
        "n_hit": 623,
        "p_hit": 0.39631,
        "t_hit_p25": 7.0,
        "t_hit_median": 19.0,
        "t_hit_p75": 32.0,
        "mdd_p25": -1.58765,
        "mdd_median": -0.66,
        "mdd_p75": -0.2462
      },
      {
        "target_pct": 3.0,
        "horizon_h": 60,
        "n_total": 1572,
        "n_hit": 695,
        "p_hit": 0.442112,
        "t_hit_p25": 8.0,
        "t_hit_median": 22.0,
        "t_hit_p75": 37.5,
        "mdd_p25": -1.57995,
        "mdd_median": -0.7065,
        "mdd_p75": -0.2654
      },
      {
        "target_pct": 3.0,
        "horizon_h": 72,
        "n_total": 1572,
        "n_hit": 747,
        "p_hit": 0.475191,
        "t_hit_p25": 9.0,
        "t_hit_median": 24.0,
        "t_hit_p75": 41.0,
        "mdd_p25": -1.5921500000000002,
        "mdd_median": -0.7677,
        "mdd_p75": -0.278
      },
      {
        "target_pct": 3.0,
        "horizon_h": 84,
        "n_total": 1572,
        "n_hit": 801,
        "p_hit": 0.509542,
        "t_hit_p25": 10.0,
        "t_hit_median": 26.0,
        "t_hit_p75": 45.0,
        "mdd_p25": -1.7573,
        "mdd_median": -0.8443,
        "mdd_p75": -0.3028
      },
      {
        "target_pct": 3.0,
        "horizon_h": 96,
        "n_total": 1572,
        "n_hit": 839,
        "p_hit": 0.533715,
        "t_hit_p25": 10.0,
        "t_hit_median": 28.0,
        "t_hit_p75": 50.0,
        "mdd_p25": -1.8248,
        "mdd_median": -0.8858,
        "mdd_p75": -0.32065
      },
      {
        "target_pct": 5.0,
        "horizon_h": 12,
        "n_total": 1572,
        "n_hit": 109,
        "p_hit": 0.069338,
        "t_hit_p25": 5.0,
        "t_hit_median": 7.0,
        "t_hit_p75": 10.0,
        "mdd_p25": -1.0979,
        "mdd_median": -0.4545,
        "mdd_p75": -0.1062
      },
      {
        "target_pct": 5.0,
        "horizon_h": 24,
        "n_total": 1572,
        "n_hit": 189,
        "p_hit": 0.120229,
        "t_hit_p25": 7.0,
        "t_hit_median": 11.0,
        "t_hit_p75": 17.0,
        "mdd_p25": -1.4206,
        "mdd_median": -0.5535,
        "mdd_p75": -0.1176
      },
      {
        "target_pct": 5.0,
        "horizon_h": 36,
        "n_total": 1572,
        "n_hit": 242,
        "p_hit": 0.153944,
        "t_hit_p25": 7.0,
        "t_hit_median": 14.0,
        "t_hit_p75": 23.0,
        "mdd_p25": -1.7819,
        "mdd_median": -0.6503,
        "mdd_p75": -0.146775
      },
      {
        "target_pct": 5.0,
        "horizon_h": 48,
        "n_total": 1572,
        "n_hit": 313,
        "p_hit": 0.199109,
        "t_hit_p25": 10.0,
        "t_hit_median": 19.0,
        "t_hit_p75": 35.0,
        "mdd_p25": -2.4694,
        "mdd_median": -0.7959,
        "mdd_p75": -0.2058
      },
      {
        "target_pct": 5.0,
        "horizon_h": 60,
        "n_total": 1572,
        "n_hit": 380,
        "p_hit": 0.24173,
        "t_hit_p25": 11.0,
        "t_hit_median": 25.0,
        "t_hit_p75": 44.0,
        "mdd_p25": -2.329475,
        "mdd_median": -0.76525,
        "mdd_p75": -0.23845
      },
      {
        "target_pct": 5.0,
        "horizon_h": 72,
        "n_total": 1572,
        "n_hit": 425,
        "p_hit": 0.270356,
        "t_hit_p25": 12.0,
        "t_hit_median": 30.0,
        "t_hit_p75": 50.0,
        "mdd_p25": -2.3232,
        "mdd_median": -0.7982,
        "mdd_p75": -0.247
      },
      {
        "target_pct": 5.0,
        "horizon_h": 84,
        "n_total": 1572,
        "n_hit": 482,
        "p_hit": 0.306616,
        "t_hit_p25": 14.0,
        "t_hit_median": 36.0,
        "t_hit_p75": 57.0,
        "mdd_p25": -2.5525249999999997,
        "mdd_median": -0.9229,
        "mdd_p75": -0.27785
      },
      {
        "target_pct": 5.0,
        "horizon_h": 96,
        "n_total": 1572,
        "n_hit": 517,
        "p_hit": 0.32888,
        "t_hit_p25": 16.0,
        "t_hit_median": 40.0,
        "t_hit_p75": 63.0,
        "mdd_p25": -2.4539,
        "mdd_median": -0.8977,
        "mdd_p75": -0.3018
      }
    ],
    "notes": [
      "Baseline probabilities are empirical from labels_v1.csv (hit-anytime within horizon).",
      "Sample size may be small early on; interpret probabilities cautiously until n_labels grows."
    ]
  }
}